starlette_core/__init__.py
starlette_core/config.py
starlette_core/database.py
starlette_core/exceptions.py
starlette_core/messages.py
starlette_core/middleware.py
starlette_core/paginator.py
starlette_core/templating.py
starlette_core/testing.py
starlette_core/utils.py
starlette_core/mail/__init__.py
starlette_core/mail/backends/__init__.py
starlette_core/mail/backends/base.py
starlette_core/mail/backends/console.py
starlette_core/mail/backends/smtp.py
starlette_core-0.0.1.dist-info/LICENSE.md
starlette_core-0.0.1.dist-info/METADATA
starlette_core-0.0.1.dist-info/WHEEL
starlette_core-0.0.1.dist-info/top_level.txt
starlette_core-0.0.1.dist-info/RECORD
