Metadata-Version: 2.1
Name: starlette-core
Version: 0.0.1
Summary: Starlette Core.
Home-page: https://github.com/accent-starlette/starlette-core
Author: Stuart George
Author-email: stuart@accentdesign.co.uk
License: MIT
Platform: UNKNOWN
Classifier: Development Status :: 3 - Alpha
Classifier: Intended Audience :: Developers
Classifier: License :: OSI Approved :: MIT License
Classifier: Operating System :: OS Independent
Classifier: Topic :: Internet :: WWW/HTTP
Classifier: Programming Language :: Python :: 3
Classifier: Programming Language :: Python :: 3.7
Classifier: Programming Language :: Python :: 3.8
Requires-Python: >=3.7
License-File: LICENSE.md
Requires-Dist: sqlalchemy
Requires-Dist: sqlalchemy-utils
Requires-Dist: starlette
Requires-Dist: typing
Requires-Dist: wtforms
Provides-Extra: docs
Requires-Dist: mkdocs ; extra == 'docs'
Requires-Dist: mkdocs-material ; extra == 'docs'
